comradewolf/__init__.py
comradewolf/universe/__init__.py
comradewolf/universe/frontend_backend_converter.py
comradewolf/universe/joins_generator.py
comradewolf/universe/olap_language_select_builders.py
comradewolf/universe/olap_prompt_converter_service.py
comradewolf/universe/olap_service.py
comradewolf/universe/olap_structure_generator.py
comradewolf/universe/possible_joins.py
comradewolf/universe/query_generator.py
comradewolf/universe/structure_generator.py
comradewolf/utils/__init__.py
comradewolf/utils/data_types.py
comradewolf/utils/enums_and_field_dicts.py
comradewolf/utils/exceptions.py
comradewolf/utils/language_specific_builders.py
comradewolf/utils/olap_data_types.py
comradewolf/utils/utils.py
comradewolf/utils/utils_for_testing.py
comradewolf-0.0.2b2.dist-info/METADATA
comradewolf-0.0.2b2.dist-info/WHEEL
comradewolf-0.0.2b2.dist-info/licenses/LICENSE
comradewolf-0.0.2b2.dist-info/RECORD
