Metadata-Version: 2.3
Name: comradewolf
Version: 0.0.2b2
Summary: Core to make OLAP-like engine. Creates SQL queries based on imported meta-data
Project-URL: Homepage, https://github.com/konstantin-suspitsyn/comradewolf
Project-URL: Issues, https://github.com/konstantin-suspitsyn/comradewolf/issues
Author-email: Konstantin Suspitsyn <konstantin.suspitsyn@xmail.ru>
Classifier: Development Status :: 4 - Beta
Classifier: Intended Audience :: Developers
Classifier: License :: OSI Approved :: Apache Software License
Classifier: Programming Language :: Python :: 3
Classifier: Programming Language :: Python :: 3 :: Only
Classifier: Programming Language :: Python :: 3.10
Classifier: Topic :: Software Development :: Code Generators
Requires-Python: >=3.10
